README.md
setup.py
rastasteady/__init__.py
rastasteady/cli.py
rastasteady/rastasteady.py
rastasteady.egg-info/PKG-INFO
rastasteady.egg-info/SOURCES.txt
rastasteady.egg-info/dependency_links.txt
rastasteady.egg-info/entry_points.txt
rastasteady.egg-info/not-zip-safe
rastasteady.egg-info/requires.txt
rastasteady.egg-info/top_level.txt
rastasteady/web/__init__.py
rastasteady/web/web.py