Metadata-Version: 1.0
Name: rastasteady
Version: 0.5.0
Summary: RastaSteady es un software de estabilizacion de video para el sistema DJI FPV digital.
Home-page: UNKNOWN
Author: UNKNOWN
Author-email: UNKNOWN
License: UNKNOWN
Platform: UNKNOWN
